{
  "numColumns": {
    "count": 6
  },
  "numRows": {
    "count": 5
  },

  "column_1": {
    "title": "Game Knowledge",
    "points": {
      "row_1": 200,
      "row_2": 400,
      "row_3": 500,
      "row_4": 800,
      "row_5": 1000
    },
    "questions": {
      "row_1": "what is the CocoaPods",
      "row_2": "Nigger",
      "row_3": "Fang",
      "row_4": "sus",
      "row_5": "gussy"
    }
  },
  "column_2": {
    "title": "Code Knowledge",
    "points": {
      "row_1": 200,
      "row_2": 400,
      "row_3": 500,
      "row_4": 800,
      "row_5": 1000
    }
  },
  "column_3": {
    "title": "Insert_title",
    "points": {
      "row_1": 200,
      "row_2": 400,
      "row_3": 500,
      "row_4": 800,
      "row_5": 1000
    }
  },
  "column_4": {
    "title": "Insert_title",
    "points": {
      "row_1": 200,
      "row_2": 400,
      "row_3": 500,
      "row_4": 800,
      "row_5": 1000
    }
  },
  "column_5": {
    "title": "Insert_title",
    "points": {
      "row_1": 200,
      "row_2": 400,
      "row_3": 500,
      "row_4": 800,
      "row_5": 1000
    }
  },
  "column_6": {
    "title": "Insert_title",
    "points": {
      "row_1": 200,
      "row_2": 400,
      "row_3": 500,
      "row_4": 800,
      "row_5": 1000
    }
  }
}